psatools/__init__.py
psatools/psatools.py
psatools-0.0.4.dist-info/LICENSE
psatools-0.0.4.dist-info/METADATA
psatools-0.0.4.dist-info/WHEEL
psatools-0.0.4.dist-info/top_level.txt
psatools-0.0.4.dist-info/RECORD
